{
	"objects":[
		{
			"type" : "floor", 
			"position": {
				"x" : 0, 
				"y" : 0, 
				"z" : 0
			}, 
			"dimensions": {
				"x" : 20,
				"y" : 1,
				"z" : 20
			}
		},
		{
			"type" : "floor",
			"position": {
				"x" : 0,
				"y" : 0,
				"z" : 20
			},
			"dimensions": {
				"x" : 20,
				"y" : 1,
				"z" : 20
			}
		},
		{
			"type" : "floor",
			"position": {
				"x" : 0,
				"y" : 0,
				"z" : 40
			},
			"dimensions": {
				"x" : 20,
				"y" : 1,
				"z" : 20
			}
		},
		{
			"type" : "floor",
			"position": {
				"x" : 20,
				"y" : 0,
				"z" : 0
			},
			"dimensions": {
				"x" : 20,
				"y" : 1,
				"z" : 20
			}
		},
		{
			"type" : "floor",
			"position": {
				"x" : 20,
				"y" : 0,
				"z" : 20
			},
			"dimensions": {
				"x" : 20,
				"y" : 1,
				"z" : 20
			}
		},
		{
			"type" : "floor",
			"position": {
				"x" : 20,
				"y" : 0,
				"z" : 40
			},
			"dimensions": {
				"x" : 20,
				"y" : 1,
				"z" : 20
			}
		},
		{
			"type" : "floor",
			"position": {
				"x" : 40,
				"y" : 0,
				"z" : 0
			},
			"dimensions": {
				"x" : 20,
				"y" : 1,
				"z" : 20
			}
		},
		{
			"type" : "floor",
			"position": {
				"x" : 40,
				"y" : 0,
				"z" : 20
			},
			"dimensions": {
				"x" : 20,
				"y" : 1,
				"z" : 20
			}
		},
		{
			"type" : "floor",
			"position": {
				"x" : 40,
				"y" : 0,
				"z" : 40
			},
			"dimensions": {
				"x" : 20,
				"y" : 1,
				"z" : 20
			}
		}
	]
}